pyqrackising/__init__.py
pyqrackising/convert_tensor_network_to_tsp.py
pyqrackising/generate_tfim_samples.py
pyqrackising/maxcut_tfim.py
pyqrackising/maxcut_tfim_sparse.py
pyqrackising/maxcut_tfim_streaming.py
pyqrackising/maxcut_tfim_util.py
pyqrackising/otoc.py
pyqrackising/spin_glass_solver.py
pyqrackising/spin_glass_solver_sparse.py
pyqrackising/spin_glass_solver_streaming.py
pyqrackising/tfim_magnetization.py
pyqrackising/tfim_square_magnetization.py
pyqrackising/tsp.py
pyqrackising/tsp_maxcut.py
pyqrackising-9.8.1.dist-info/LICENSE.md
pyqrackising-9.8.1.dist-info/METADATA
pyqrackising-9.8.1.dist-info/WHEEL
pyqrackising-9.8.1.dist-info/top_level.txt
pyqrackising-9.8.1.dist-info/RECORD
