Metadata-Version: 2.1
Name: pyqrackising
Version: 9.8.1
Summary: Fast MAXCUT, TSP, and sampling heuristics from near-ideal transverse field Ising model (TFIM)
Home-page: https://github.com/vm6502q/PyQrackIsing
Author: Dan Strano
Author-email: stranoj@gmail.com
License: LGPL-3.0-or-later
Platform: UNKNOWN
Classifier: Environment :: Console
Classifier: Intended Audience :: Developers
Classifier: Intended Audience :: Science/Research
Classifier: Programming Language :: C++
Classifier: Programming Language :: Python :: 3.8
Classifier: Programming Language :: Python :: 3.9
Classifier: Programming Language :: Python :: 3.10
Classifier: Topic :: Scientific/Engineering
License-File: LICENSE.md
